{
  "date": "2026-07-24T194234Z",
  "day": "2026-07-24",
  "sourceKey": "weiboRealtime",
  "savedAt": "2026-07-24T19:42:34Z",
  "label": "实时",
  "description": "微博实时上升榜（按上榜时间排序，2026-07-24，共 30 条，约每 6 小时更新）",
  "updateFrequency": "every-6h",
  "fetchedDate": "2026-07-24",
  "items": [
    {
      "title": "方星海涉嫌严重违纪违法",
      "description": "新 · 国内时政",
      "url": "https://s.weibo.com/weibo?q=%23%E6%96%B9%E6%98%9F%E6%B5%B7%E6%B6%89%E5%AB%8C%E4%B8%A5%E9%87%8D%E8%BF%9D%E7%BA%AA%E8%BF%9D%E6%B3%95%23&t=31&band_rank=1&Refer=top",
      "score": 83130,
      "owner": "微博实时",
      "label": "新",
      "category": "国内时政",
      "onboardTime": 1784921834
    },
    {
      "title": "49岁男子杀害82岁老师细节曝光",
      "description": "新 · 突发/灾害",
      "url": "https://s.weibo.com/weibo?q=%2349%E5%B2%81%E7%94%B7%E5%AD%90%E6%9D%80%E5%AE%B382%E5%B2%81%E8%80%81%E5%B8%88%E7%BB%86%E8%8A%82%E6%9B%9D%E5%85%89%23&t=31&band_rank=1&Refer=top",
      "score": 41183,
      "owner": "微博实时",
      "label": "新",
      "category": "突发/灾害",
      "onboardTime": 1784920874
    },
    {
      "title": "KPL夏季赛卡位赛",
      "description": "新 · 电竞",
      "url": "https://s.weibo.com/weibo?q=%23KPL%E5%A4%8F%E5%AD%A3%E8%B5%9B%E5%8D%A1%E4%BD%8D%E8%B5%9B%23&t=31&band_rank=1&Refer=top",
      "score": 41224,
      "owner": "微博实时",
      "label": "新",
      "category": "电竞",
      "onboardTime": 1784920095
    },
    {
      "title": "台风红霞逼近广东强度将爆发",
      "description": "新 · 民生新闻",
      "url": "https://s.weibo.com/weibo?q=%23%E5%8F%B0%E9%A3%8E%E7%BA%A2%E9%9C%9E%E9%80%BC%E8%BF%91%E5%B9%BF%E4%B8%9C%E5%BC%BA%E5%BA%A6%E5%B0%86%E7%88%86%E5%8F%91%23&t=31&band_rank=1&Refer=top",
      "score": 68111,
      "owner": "微博实时",
      "label": "新",
      "category": "民生新闻",
      "onboardTime": 1784916975
    },
    {
      "title": "荷兰弟说逛上海是赞达亚做攻略",
      "description": "电影",
      "url": "https://s.weibo.com/weibo?q=%23%E8%8D%B7%E5%85%B0%E5%BC%9F%E8%AF%B4%E9%80%9B%E4%B8%8A%E6%B5%B7%E6%98%AF%E8%B5%9E%E8%BE%BE%E4%BA%9A%E5%81%9A%E6%94%BB%E7%95%A5%23&t=31&band_rank=1&Refer=top",
      "score": 41182,
      "owner": "微博实时",
      "label": "",
      "category": "电影",
      "onboardTime": 1784916555
    },
    {
      "title": "韦东奕课后向王虹追问请教",
      "description": "教育",
      "url": "https://s.weibo.com/weibo?q=%23%E9%9F%A6%E4%B8%9C%E5%A5%95%E8%AF%BE%E5%90%8E%E5%90%91%E7%8E%8B%E8%99%B9%E8%BF%BD%E9%97%AE%E8%AF%B7%E6%95%99%23&t=31&band_rank=1&Refer=top",
      "score": 51371,
      "owner": "微博实时",
      "label": "",
      "category": "教育",
      "onboardTime": 1784915177
    },
    {
      "title": "汪苏泷演唱会戴了光环戒指",
      "description": "演出",
      "url": "https://s.weibo.com/weibo?q=%23%E6%B1%AA%E8%8B%8F%E6%B3%B7%E6%BC%94%E5%94%B1%E4%BC%9A%E6%88%B4%E4%BA%86%E5%85%89%E7%8E%AF%E6%88%92%E6%8C%87%23&t=31&band_rank=1&Refer=top",
      "score": 41200,
      "owner": "微博实时",
      "label": "",
      "category": "演出",
      "onboardTime": 1784914576
    },
    {
      "title": "爸妈吵架都走了男孩抱妹妹找奶奶",
      "description": "民生新闻",
      "url": "https://s.weibo.com/weibo?q=%23%E7%88%B8%E5%A6%88%E5%90%B5%E6%9E%B6%E9%83%BD%E8%B5%B0%E4%BA%86%E7%94%B7%E5%AD%A9%E6%8A%B1%E5%A6%B9%E5%A6%B9%E6%89%BE%E5%A5%B6%E5%A5%B6%23&t=31&band_rank=1&Refer=top",
      "score": 41225,
      "owner": "微博实时",
      "label": "",
      "category": "民生新闻",
      "onboardTime": 1784912657
    },
    {
      "title": "靠出轨剧情出海小游戏日入338万",
      "description": "游戏",
      "url": "https://s.weibo.com/weibo?q=%23%E9%9D%A0%E5%87%BA%E8%BD%A8%E5%89%A7%E6%83%85%E5%87%BA%E6%B5%B7%E5%B0%8F%E6%B8%B8%E6%88%8F%E6%97%A5%E5%85%A5338%E4%B8%87%23&t=31&band_rank=1&Refer=top",
      "score": 47264,
      "owner": "微博实时",
      "label": "",
      "category": "游戏",
      "onboardTime": 1784912118
    },
    {
      "title": "男生中考699分偷偷改志愿读中职",
      "description": "热 · 民生新闻",
      "url": "https://s.weibo.com/weibo?q=%23%E7%94%B7%E7%94%9F%E4%B8%AD%E8%80%83699%E5%88%86%E5%81%B7%E5%81%B7%E6%94%B9%E5%BF%97%E6%84%BF%E8%AF%BB%E4%B8%AD%E8%81%8C%23&t=31&band_rank=1&Refer=top",
      "score": 62754,
      "owner": "微博实时",
      "label": "热",
      "category": "民生新闻",
      "onboardTime": 1784911398
    },
    {
      "title": "演唱会黄牛被抓时面前好几排手机",
      "description": "民生新闻",
      "url": "https://s.weibo.com/weibo?q=%23%E6%BC%94%E5%94%B1%E4%BC%9A%E9%BB%84%E7%89%9B%E8%A2%AB%E6%8A%93%E6%97%B6%E9%9D%A2%E5%89%8D%E5%A5%BD%E5%87%A0%E6%8E%92%E6%89%8B%E6%9C%BA%23&t=31&band_rank=1&Refer=top",
      "score": 41208,
      "owner": "微博实时",
      "label": "",
      "category": "民生新闻",
      "onboardTime": 1784910619
    },
    {
      "title": "王源回复魏如萱",
      "description": "综艺",
      "url": "https://s.weibo.com/weibo?q=%23%E7%8E%8B%E6%BA%90%E5%9B%9E%E5%A4%8D%E9%AD%8F%E5%A6%82%E8%90%B1%23&t=31&band_rank=1&Refer=top",
      "score": 41190,
      "owner": "微博实时",
      "label": "",
      "category": "综艺",
      "onboardTime": 1784910499
    },
    {
      "title": "Gucci给这一秒过火投广",
      "description": "剧集,时尚",
      "url": "https://s.weibo.com/weibo?q=%23Gucci%E7%BB%99%E8%BF%99%E4%B8%80%E7%A7%92%E8%BF%87%E7%81%AB%E6%8A%95%E5%B9%BF%23&t=31&band_rank=1&Refer=top",
      "score": 41217,
      "owner": "微博实时",
      "label": "",
      "category": "剧集,时尚",
      "onboardTime": 1784910379
    },
    {
      "title": "鹭卓发文不忘来时路",
      "description": "综艺",
      "url": "https://s.weibo.com/weibo?q=%E9%B9%AD%E5%8D%93%E5%8F%91%E6%96%87%E4%B8%8D%E5%BF%98%E6%9D%A5%E6%97%B6%E8%B7%AF&t=31&band_rank=1&Refer=top",
      "score": 41671,
      "owner": "微博实时",
      "label": "",
      "category": "综艺",
      "onboardTime": 1784910080
    },
    {
      "title": "出师表翻译成日语再翻回来",
      "description": "幽默",
      "url": "https://s.weibo.com/weibo?q=%E5%87%BA%E5%B8%88%E8%A1%A8%E7%BF%BB%E8%AF%91%E6%88%90%E6%97%A5%E8%AF%AD%E5%86%8D%E7%BF%BB%E5%9B%9E%E6%9D%A5&t=31&band_rank=1&Refer=top",
      "score": 41243,
      "owner": "微博实时",
      "label": "",
      "category": "幽默",
      "onboardTime": 1784909898
    },
    {
      "title": "一招区分动物奶油和植物奶油",
      "description": "科学科普",
      "url": "https://s.weibo.com/weibo?q=%E4%B8%80%E6%8B%9B%E5%8C%BA%E5%88%86%E5%8A%A8%E7%89%A9%E5%A5%B6%E6%B2%B9%E5%92%8C%E6%A4%8D%E7%89%A9%E5%A5%B6%E6%B2%B9&t=31&band_rank=1&Refer=top",
      "score": 65715,
      "owner": "微博实时",
      "label": "",
      "category": "科学科普",
      "onboardTime": 1784909300
    },
    {
      "title": "感觉宋威龙好会谈恋爱",
      "description": "剧集",
      "url": "https://s.weibo.com/weibo?q=%E6%84%9F%E8%A7%89%E5%AE%8B%E5%A8%81%E9%BE%99%E5%A5%BD%E4%BC%9A%E8%B0%88%E6%81%8B%E7%88%B1&t=31&band_rank=1&Refer=top",
      "score": 60239,
      "owner": "微博实时",
      "label": "",
      "category": "剧集",
      "onboardTime": 1784909120
    },
    {
      "title": "王虹告诉我们天才可以云淡风轻",
      "description": "教育",
      "url": "https://s.weibo.com/weibo?q=%E7%8E%8B%E8%99%B9%E5%91%8A%E8%AF%89%E6%88%91%E4%BB%AC%E5%A4%A9%E6%89%8D%E5%8F%AF%E4%BB%A5%E4%BA%91%E6%B7%A1%E9%A3%8E%E8%BD%BB&t=31&band_rank=1&Refer=top",
      "score": 41219,
      "owner": "微博实时",
      "label": "",
      "category": "教育",
      "onboardTime": 1784909120
    },
    {
      "title": "詹姆斯底薪",
      "description": "体育",
      "url": "https://s.weibo.com/weibo?q=%E8%A9%B9%E5%A7%86%E6%96%AF%E5%BA%95%E8%96%AA&t=31&band_rank=1&Refer=top",
      "score": 60080,
      "owner": "微博实时",
      "label": "",
      "category": "体育",
      "onboardTime": 1784909060
    },
    {
      "title": "詹姆斯发长文",
      "description": "体育",
      "url": "https://s.weibo.com/weibo?q=%E8%A9%B9%E5%A7%86%E6%96%AF%E5%8F%91%E9%95%BF%E6%96%87&t=31&band_rank=1&Refer=top",
      "score": 117293,
      "owner": "微博实时",
      "label": "",
      "category": "体育",
      "onboardTime": 1784909001
    },
    {
      "title": "汪苏泷肩带掉了",
      "description": "演出",
      "url": "https://s.weibo.com/weibo?q=%23%E6%B1%AA%E8%8B%8F%E6%B3%B7%E8%82%A9%E5%B8%A6%E6%8E%89%E4%BA%86%23&t=31&band_rank=1&Refer=top",
      "score": 47754,
      "owner": "微博实时",
      "label": "",
      "category": "演出",
      "onboardTime": 1784909001
    },
    {
      "title": "薛之谦演唱会",
      "description": "演出",
      "url": "https://s.weibo.com/weibo?q=%E8%96%9B%E4%B9%8B%E8%B0%A6%E6%BC%94%E5%94%B1%E4%BC%9A&t=31&band_rank=1&Refer=top",
      "score": 41248,
      "owner": "微博实时",
      "label": "",
      "category": "演出",
      "onboardTime": 1784908461
    },
    {
      "title": "76人阵容",
      "description": "体育",
      "url": "https://s.weibo.com/weibo?q=%2376%E4%BA%BA%E9%98%B5%E5%AE%B9%23&t=31&band_rank=1&Refer=top",
      "score": 51746,
      "owner": "微博实时",
      "label": "",
      "category": "体育",
      "onboardTime": 1784908401
    },
    {
      "title": "耳帝评价歌手",
      "description": "综艺",
      "url": "https://s.weibo.com/weibo?q=%E8%80%B3%E5%B8%9D%E8%AF%84%E4%BB%B7%E6%AD%8C%E6%89%8B&t=31&band_rank=1&Refer=top",
      "score": 41248,
      "owner": "微博实时",
      "label": "",
      "category": "综艺",
      "onboardTime": 1784908280
    },
    {
      "title": "詹姆斯加盟76人",
      "description": "体育",
      "url": "https://s.weibo.com/weibo?q=%E8%A9%B9%E5%A7%86%E6%96%AF%E5%8A%A0%E7%9B%9F76%E4%BA%BA&t=31&band_rank=1&Refer=top",
      "score": 278906,
      "owner": "微博实时",
      "label": "",
      "category": "体育",
      "onboardTime": 1784907979
    },
    {
      "title": "张凌赫演的生理性面部抽搐",
      "description": "剧集",
      "url": "https://s.weibo.com/weibo?q=%23%E5%BC%A0%E5%87%8C%E8%B5%AB%E6%BC%94%E7%9A%84%E7%94%9F%E7%90%86%E6%80%A7%E9%9D%A2%E9%83%A8%E6%8A%BD%E6%90%90%23&t=31&band_rank=1&Refer=top",
      "score": 44316,
      "owner": "微博实时",
      "label": "",
      "category": "剧集",
      "onboardTime": 1784907860
    },
    {
      "title": "父亲为初恋想离婚要分女儿630万房款",
      "description": "民生新闻",
      "url": "https://s.weibo.com/weibo?q=%23%E7%88%B6%E4%BA%B2%E4%B8%BA%E5%88%9D%E6%81%8B%E6%83%B3%E7%A6%BB%E5%A9%9A%E8%A6%81%E5%88%86%E5%A5%B3%E5%84%BF630%E4%B8%87%E6%88%BF%E6%AC%BE%23&t=31&band_rank=1&Refer=top",
      "score": 48123,
      "owner": "微博实时",
      "label": "",
      "category": "民生新闻",
      "onboardTime": 1784907740
    },
    {
      "title": "赵小童是天使",
      "description": "热 · 演出",
      "url": "https://s.weibo.com/weibo?q=%E8%B5%B5%E5%B0%8F%E7%AB%A5%E6%98%AF%E5%A4%A9%E4%BD%BF&t=31&band_rank=1&Refer=top",
      "score": 100603,
      "owner": "微博实时",
      "label": "热",
      "category": "演出",
      "onboardTime": 1784907260
    },
    {
      "title": "许嵩演唱会",
      "description": "演出",
      "url": "https://s.weibo.com/weibo?q=%E8%AE%B8%E5%B5%A9%E6%BC%94%E5%94%B1%E4%BC%9A&t=31&band_rank=1&Refer=top",
      "score": 41187,
      "owner": "微博实时",
      "label": "",
      "category": "演出",
      "onboardTime": 1784907260
    },
    {
      "title": "把豆包逼出来幸福者退让了",
      "description": "幽默",
      "url": "https://s.weibo.com/weibo?q=%E6%8A%8A%E8%B1%86%E5%8C%85%E9%80%BC%E5%87%BA%E6%9D%A5%E5%B9%B8%E7%A6%8F%E8%80%85%E9%80%80%E8%AE%A9%E4%BA%86&t=31&band_rank=1&Refer=top",
      "score": 50218,
      "owner": "微博实时",
      "label": "",
      "category": "幽默",
      "onboardTime": 1784906482
    }
  ]
}
